magic/__init__.py
magic/londrina.py
magiclondrina-0.0.8.dist-info/METADATA
magiclondrina-0.0.8.dist-info/WHEEL
magiclondrina-0.0.8.dist-info/top_level.txt
magiclondrina-0.0.8.dist-info/RECORD
