Metadata-Version: 2.1
Name: magiclondrina
Version: 0.0.8
Summary: Buscador de cartas de magic em londrina
Home-page: https://github.com/erickhiroyuki/pipinstallmagic
Author: Erick
Author-email: erickomine67@gmail.com
Requires-Python: >=3.8
Requires-Dist: beautifulsoup4 (==4.11.1)
Requires-Dist: lxml (==4.9.1)
Requires-Dist: scrython (==1.11.0)
Requires-Dist: requests (==2.28.1)
Requires-Dist: tabulate (==0.9.0)
